aioslurm/__init__.py
aioslurm/__main__.py
aioslurm/exceptions.py
aioslurm/py.typed
aioslurm/sbatch.py
aioslurm/settings.py
aioslurm/utils/__init__.py
aioslurm/utils/click.py
aioslurm/utils/exceptions.py
aioslurm/utils/subprocess.py
aioslurm-0.1.0.dist-info/AUTHORS.rst
aioslurm-0.1.0.dist-info/LICENSE
aioslurm-0.1.0.dist-info/METADATA
aioslurm-0.1.0.dist-info/WHEEL
aioslurm-0.1.0.dist-info/entry_points.txt
aioslurm-0.1.0.dist-info/top_level.txt
aioslurm-0.1.0.dist-info/RECORD
